{"stats":{"minecraft:used":{"minecraft:netherite_sword":41},"minecraft:killed":{"minecraft:piglin_brute":5},"minecraft:custom":{"minecraft:jump":26,"minecraft:open_chest":28,"minecraft:time_since_rest":2728,"minecraft:deaths":1,"minecraft:damage_dealt":2973,"minecraft:crouch_one_cm":5,"minecraft:sprint_one_cm":6816,"minecraft:play_time":7801,"minecraft:time_since_death":2707,"minecraft:walk_one_cm":5558,"minecraft:sneak_time":149,"minecraft:total_world_time":7810,"minecraft:mob_kills":6,"minecraft:fly_one_cm":85560}},"DataVersion":3955}